mm_web3/__init__.py
mm_web3/account.py
mm_web3/calcs.py
mm_web3/config.py
mm_web3/log.py
mm_web3/network.py
mm_web3/node.py
mm_web3/proxy.py
mm_web3/py.typed
mm_web3/retry.py
mm_web3/utils.py
mm_web3/validators.py
mm_web3-0.5.7.dist-info/METADATA
mm_web3-0.5.7.dist-info/WHEEL
mm_web3-0.5.7.dist-info/RECORD
