Metadata-Version: 2.4
Name: mm-web3
Version: 0.5.7
Requires-Python: >=3.13
Requires-Dist: loguru>=0.7.3
Requires-Dist: mm-http~=0.2.5
Requires-Dist: mm-print~=0.2.2
Requires-Dist: mm-std~=0.6.0
